pylevers/__init__.py
pylevers/version.py
pylevers/core/__init__.py
pylevers/core/client.py
pylevers/core/handlers.py
pylevers/core/types.py
pylevers/proto/common_pb2.py
pylevers/proto/common_pb2_grpc.py
pylevers/proto/levers_pb2.py
pylevers/proto/levers_pb2_grpc.py
pylevers/proto/schema_pb2.py
pylevers/proto/schema_pb2_grpc.py
pylevers-0.1.0.dist-info/LICENSE
pylevers-0.1.0.dist-info/METADATA
pylevers-0.1.0.dist-info/WHEEL
pylevers-0.1.0.dist-info/top_level.txt
pylevers-0.1.0.dist-info/RECORD
